guitarHarmony/__init__.py
guitarHarmony/chord.py
guitarHarmony/exercise.py
guitarHarmony/helper.py
guitarHarmony/interval.py
guitarHarmony/note.py
guitarHarmony/progression.py
guitarHarmony/register.py
guitarHarmony/scale.py
guitarHarmony/stream.py
guitarHarmony/style.py
test/__init__.py
test/test_chord.py
test/test_interval.py
test/test_note.py
guitarHarmony-0.5.9.dist-info/LICENSE.txt
guitarHarmony-0.5.9.dist-info/METADATA
guitarHarmony-0.5.9.dist-info/WHEEL
guitarHarmony-0.5.9.dist-info/top_level.txt
guitarHarmony-0.5.9.dist-info/RECORD
