Metadata-Version: 2.1
Name: guitarHarmony
Version: 0.5.9
Summary: A python wrapper to learn music theory in Guitar.
Home-page: https://github.com/heeryerate/Guitar-Harmony
Author: Esparami
Author-email: heeryerate@gmail.com
License: UNKNOWN
Download-URL: https://bitbucket.org/Xi_He/music-theory/get/0.5.9.zip
Keywords: music,theory,guitar,harmony
Platform: UNKNOWN
Classifier: Programming Language :: Python :: 3
Classifier: License :: OSI Approved :: MIT License
Classifier: Operating System :: OS Independent
Requires-Python: >=3.6
